bjam_toolbox/__init__.py
bjam_toolbox/__main__.py
bjam_toolbox/launcher.py
bjam_toolbox/common/__init__.py
bjam_toolbox/common/dataio.py
bjam_toolbox/common/utils.py
bjam_toolbox/defaults/__init__.py
bjam_toolbox/defaults/config.json
bjam_toolbox/defaults/config_loader.py
bjam_toolbox/dimensional/__init__.py
bjam_toolbox/dimensional/analysis.py
bjam_toolbox/dimensional/geometry.py
bjam_toolbox/dimensional/gui.py
bjam_toolbox/ink_concentration/__init__.py
bjam_toolbox/ink_concentration/analyzer.py
bjam_toolbox/ink_concentration/bayesian_classifier.py
bjam_toolbox/ink_concentration/classification.py
bjam_toolbox/ink_concentration/concentration_estimator.py
bjam_toolbox/ink_concentration/gui.py
bjam_toolbox/ink_concentration/main.py
bjam_toolbox/ink_concentration/menu.py
bjam_toolbox/ink_concentration/plots.py
bjam_toolbox/ink_concentration/plotting.py
bjam_toolbox/ink_concentration/sample_data/__init__.py
bjam_toolbox/ink_concentration/sample_data/chroma_training_data.csv
bjam_toolbox/ink_concentration/sample_data/test_5petro_25IPA.csv
bjam_toolbox/ink_concentration/sample_data/test_bayesian_3class.csv
bjam_toolbox/ink_concentration/sample_data/test_concentration.csv
bjam_toolbox-2.2.0.dist-info/licenses/LICENSE
bjam_toolbox-2.2.0.dist-info/METADATA
bjam_toolbox-2.2.0.dist-info/WHEEL
bjam_toolbox-2.2.0.dist-info/entry_points.txt
bjam_toolbox-2.2.0.dist-info/top_level.txt
bjam_toolbox-2.2.0.dist-info/RECORD
