Metadata-Version: 2.4
Name: bjam-toolbox
Version: 2.2.0
Summary: Tools for Binder Jet Additive Manufacturing process analysis
Author-email: "Matthew L. McCoy" <matthew.mccoy@gatech.edu>
License-Expression: MIT
Project-URL: Homepage, https://github.com/mattlmccoy/rfam-toolbox
Project-URL: Repository, https://github.com/mattlmccoy/rfam-toolbox
Project-URL: Issues, https://github.com/mattlmccoy/rfam-toolbox/issues
Classifier: Development Status :: 4 - Beta
Classifier: Intended Audience :: Science/Research
Classifier: Topic :: Scientific/Engineering :: Image Processing
Classifier: Operating System :: OS Independent
Classifier: Programming Language :: Python :: 3
Classifier: Programming Language :: Python :: 3.9
Classifier: Programming Language :: Python :: 3.10
Classifier: Programming Language :: Python :: 3.11
Classifier: Programming Language :: Python :: 3.12
Requires-Python: >=3.9
License-File: LICENSE
Requires-Dist: opencv-python>=4.5.0
Requires-Dist: numpy>=1.20.0
Requires-Dist: matplotlib>=3.4.0
Requires-Dist: pandas>=1.3.0
Requires-Dist: scikit-image>=0.18.0
Requires-Dist: scikit-learn>=1.0.0
Requires-Dist: scipy>=1.7.0
Requires-Dist: seaborn>=0.12.0
Requires-Dist: pdf2image>=1.14.0
Provides-Extra: dev
Requires-Dist: pytest>=6.0; extra == "dev"
Requires-Dist: pytest-cov>=2.0; extra == "dev"
Requires-Dist: black>=21.0; extra == "dev"
Requires-Dist: flake8>=3.9; extra == "dev"
Requires-Dist: build; extra == "dev"
Requires-Dist: twine; extra == "dev"
Dynamic: license-file
